{"Red": ["#feccc2", "#fdbdbb", "#845952", "#ecb0a2", "#dda09b", "#fed2c8", "#9e7168", "#fcb3a6", "#ca8e88", "#b87171", "#f7a190", "#7f544c", "#eca1a0", "#fdc8bd", "#a67b75", "#b18779", "#e19591", "#ecbabb", "#8d625c", "#d88887", "#e6b1af", "#fed0c3", "#d19795", "#a4786b", "#986b5e", "#fbab9d", "#fdc3c2", "#c9837c", "#bc7b7b", "#8a5748", "#976d65", "#feccbe", "#b27461", "#f1bbb0", "#fdbbae", "#f1c7c0", "#f8cec7", "#ad8175", "#e2a8a6", "#d5aca2", "#fcc2b3", "#bd8586", "#fdc5b9", "#8a5d56", "#936758", "#a27272"], "Orange": ["#794e3d", "#b68b7c", "#69412e", "#d49456", "#5e321e", "#9b5c23", "#a97f6d", "#ce9f8b", "#8d6250", "#ebac68", "#fde4c0", "#4f1e0a", "#fdd6c5", "#fccab7", "#f3c282", "#f7c79e", "#6e4435", "#9f6851", "#814922", "#a0705e", "#603a2a", "#8d5534", "#bc947f", "#be7f4a", "#c58a61", "#7e5343", "#e8cda6", "#aa8357", "#522d1c", "#d89871", "#fddab0", "#753912", "#d1a997", "#e3bf8f", "#ddaf7f", "#fcd697", "#9b6641", "#dab6a0", "#622a0a", "#ae6f39", "#724b3a", "#c9a573", "#b28c6f"], "Yellow": [], "Yellow Green": [], "Green": [], "Blue Green": [], "Light Blue": [], "Blue": ["#3d72ab", "#154c82", "#6a93b0", "#2d4b79", "#a2cce1", "#b2d5ec", "#062554", "#5d78ad", "#3783c5", "#77afd8", "#0e53a6", "#356696", "#1e3962", "#182952", "#012373", "#8ecef3", "#c0e7fa", "#5c8fbe", "#4d84a9", "#266bae", "#385880", "#46688c", "#25578c", "#52a1d6", "#0d3b72", "#78a0c2", "#22456b", "#03378c", "#50739b", "#0f2f61", "#8dbfdf"], "Dark Blue": ["#323672", "#777fbb", "#030d47", "#9da1ee", "#4b4d7c", "#5f6496", "#858bb6", "#7f7ccb", "#6861a2", "#4c5685", "#535099", "#01115e", "#3d4f91", "#798ac7", "#c8c8fc", "#010635", "#8d8fdd", "#9ea8d2", "#6f6daf", "#433f7a", "#adb1f8", "#59598b"], "Blue Violet": ["#8c5aa4", "#8b72b4", "#9f76bb", "#84579f", "#694986", "#9864b0", "#6a5391", "#7c5398", "#8465ad", "#956eb0", "#8e5da9", "#a67ec4", "#967cc6", "#9b66b7", "#704c8b", "#80559b", "#8659a4", "#8e66a5", "#765092", "#9260ad", "#aa85d2"], "Violet": ["#c191c4", "#8d5a93"], "Violet Red": [], "Grey": ["#b4b6c6", "#edded4", "#8a8a8f", "#554d4d", "#bba08c", "#58577b", "#8d7a57", "#d9b2aa", "#e0dfe4", "#4d3127", "#9d7871", "#cfcfd4", "#9999a3", "#ab817b", "#716566", "#273d54", "#5a5b65", "#e4cfc3", "#afaead", "#687682", "#d8bdbb", "#3e4054", "#35385f", "#ccada1", "#282b52", "#514576", "#ecedf0", "#bb9f9b", "#aa8b88", "#c5c7d4", "#39526a", "#919fc3", "#af8ec5", "#4b4d58", "#696c90", "#55555a", "#b29491", "#d5e6f0", "#42424e", "#a4a6b5", "#74818b", "#7c7172", "#ddc3ba", "#c6a597", "#babfd1", "#5c4c45", "#b2b1b6", "#c4a8a6", "#d8d8dc", "#e9c5b4", "#c6c6cb", "#453968", "#9a9cab", "#909095", "#2f335b", "#e7e7eb", "#bbbbc1", "#7e7f84", "#866666", "#42596f", "#cfd0df", "#857a78", "#bcb5b0", "#6a879e", "#b89587", "#ead8d0", "#655956", "#e4c5c5", "#8686a2", "#998880", "#ede2dd", "#464753", "#68686d", "#2e465f", "#7d7d97", "#aa9b93", "#dbacc7", "#636486", "#acb0c2", "#5f5e62", "#c19d8f", "#a2a3ac", "#717278", "#edd3c9", "#4e505d", "#7a605b", "#decec9", "#98bacf", "#5f6271", "#726f99", "#5d427c", "#c3acb2", "#556b7a", "#cfb3b4", "#b6a6a0", "#c5dce4", "#c1c3ce", "#c8b6b0", "#dbc9c1", "#3c3f51", "#e1bdab", "#a4839b", "#515256", "#424369", "#abc1d6", "#a19694", "#e2e3ea", "#82719f", "#d3d3d9", "#916c6b", "#ce9fc1", "#63435a", "#dbdde8", "#4d3c6e", "#d8b8b2", "#e2dcd7", "#eaceba", "#49494e", "#5f3d37", "#cda39e", "#59595e", "#2a4159", "#906862", "#96969b", "#9a7980", "#454859", "#a78cba", "#3e3561", "#c3a7da", "#c0c0c5", "#e5d4cc", "#c0a89c", "#2e2a50", "#c7b796", "#998d8b", "#9eb1bb", "#515274", "#b0908c", "#37315d", "#bdada6", "#84848b", "#9193a1", "#7a8d9d", "#3c3c66", "#7e678a", "#c5b1a9", "#a09e9c", "#805f4a", "#724d64", "#b4b5c1", "#587187", "#cdabab", "#5d5251", "#ccc0c1", "#b18f80", "#bf93b0", "#d4c4bd", "#69534a", "#f0ccd5", "#edd3c1", "#83635c", "#abacb6", "#646a78", "#8e8480", "#be988a", "#ad95a2", "#9a82b2", "#b79a97", "#6d6c85", "#414355", "#514846", "#593b4c", "#543932", "#cacbd9", "#4d2b3e", "#322f56", "#a78774", "#d8bfb3", "#6e6d71", "#734d46", "#c39898", "#8caec2", "#e6e8f1", "#8ea2b1", "#9ca1b3", "#8e647c", "#a3807c", "#b68e84", "#7b6d66", "#637c93", "#cfccc5", "#24384f", "#e3c8bc", "#b6b7bb", "#bbcedb", "#563427", "#a59388", "#bb9190", "#4b6175", "#917e75", "#a9a5a3", "#535a67", "#e9bbcf", "#66473f", "#4c4d52", "#515461", "#635d7e", "#957375", "#324b64", "#cebdb6", "#3a3c4e", "#55443c", "#e7e5e1", "#a7a9bd", "#907ca7", "#87746c", "#dad2b1", "#7f629c", "#624781", "#636368", "#77797e", "#e2bdb5", "#c8a99d", "#bdbfca", "#75758e", "#b8bbc9", "#b0a19a", "#b99991", "#7b5776", "#b69acc", "#6d605c", "#9c7d68", "#8c8e9c", "#859aa1", "#f0e8e7", "#c5a193", "#a68781", "#9193ab", "#dbdbe1", "#afb0bc", "#d2b8ac", "#d9d4d0", "#2b2d56", "#d5d6e3", "#472f57", "#755951", "#f2d9c8", "#b08781", "#a8a8ae", "#858895", "#b6a8aa", "#cfb2a7", "#9d7d77", "#5d4f6f", "#bfa3a1", "#a9bcc6", "#927092", "#5b5e6b", "#40535e", "#50415e", "#a08288", "#7880a8", "#494c5d", "#c0a194", "#705f8d", "#563e75", "#cacbd0", "#c3bdb9", "#9f9fa6", "#d7c5cc", "#98726d", "#7c99b1", "#494a6e"], "Black": ["#01050b", "#2c2b37", "#141821", "#1e212d", "#060e18", "#353749", "#172738", "#050814", "#201a20", "#0b1723", "#111d2e", "#11151d", "#20222f", "#2f2523", "#191719", "#252734", "#2d2f40", "#403836", "#0e0d0d", "#1b1d29", "#3b3b47", "#0a111c", "#363538", "#040409", "#02050f", "#0e1a28", "#1b2c3e", "#26252c", "#0f1118", "#162333", "#141313", "#392018", "#211f25", "#282a38", "#121a24", "#0a0e16", "#38302e", "#1a1a24", "#262221", "#0c151f", "#040b15", "#4c4343", "#2e313a", "#203042", "#222531", "#292b33", "#0f1822", "#050911", "#2f292e", "#3a393d", "#323446", "#14202e", "#1f1b1a", "#2f150c", "#1e1f29", "#18171d", "#010611", "#131d29", "#02060c", "#070b13", "#4a3f3c", "#3f261e", "#292625", "#23232e", "#373a4c", "#21354b", "#010318", "#190208", "#0e1824", "#2d2f3c", "#21212a", "#171516", "#30323e", "#0c1019", "#14193c", "#2c2f36", "#1f1d1d", "#0a0e19", "#03030b", "#1c1b20", "#3f2c27", "#030710", "#22201f", "#070b16", "#2a2d3a", "#0f131c", "#262835", "#3d3f44", "#26274c", "#2a2d36", "#131319", "#424247", "#232635", "#272830", "#0b1420", "#1b1b27", "#060915", "#171820", "#24272f", "#05050d", "#1e1d23", "#020409", "#2d2c2b", "#3a1a0e", "#080c14", "#24232a", "#050a12", "#36373e", "#202245", "#101c2a", "#19293c", "#1f1314", "#2b211f", "#16151b", "#161a24", "#30333b", "#09101b", "#403e40", "#3c3432", "#121e2c", "#3b1e31", "#05132b", "#090d15", "#050c17", "#14161d", "#2d2d32", "#313133", "#212332", "#040612", "#192939", "#07070f", "#0e0f15", "#0d1620", "#221d1b", "#363743", "#272127", "#212430", "#472b21", "#342b28", "#0b131d", "#030813", "#0c141e", "#292c38", "#251835", "#24242f", "#272936", "#3f3f4b", "#101a26", "#35221d", "#0b0207", "#181c23", "#121010", "#1b1f26", "#130a2a", "#0c2444", "#0a0b10", "#252424", "#111923", "#061b38", "#2a272b", "#181822", "#1f1f2b", "#152231", "#302143", "#323139", "#0c1826", "#281a16", "#2a2c3e", "#242632", "#21212d", "#21252d", "#281b1e", "#45464a", "#493a32", "#131620", "#070f19", "#1f1009", "#02091d", "#18212c", "#1e1d26", "#08101a", "#312f2d", "#111c27", "#2d2827", "#191715", "#1a191f", "#152536", "#1f222e", "#01040e", "#311c17", "#111821", "#040810", "#342c33", "#161f2a", "#1c1a1a", "#303242", "#1c1817", "#1d1f2c", "#203247", "#0c1622", "#2a2931", "#452217", "#192636", "#171512", "#0f1720", "#3b314a", "#3a3b42", "#0e111b", "#44322e", "#443744", "#443b3a", "#0b0f17", "#191b27", "#090c18", "#010425", "#33343e", "#1d2f43", "#05060b", "#232228", "#392722", "#2d3038", "#04070e"], "White": ["#fefcf8", "#fef2e3", "#fedbce", "#fee6d7", "#fef3e8", "#f1f2f5", "#fefefe", "#fefbf0", "#feecdc", "#fddfd2", "#e0d9fc", "#fdf4f0", "#daf5fc", "#f5f4fc", "#f7ece2", "#fed6cc", "#eeebf8", "#f5dfcf", "#fdf1df", "#fdf6e4", "#f7fdfe", "#f9e4d4", "#fefbf3", "#f6d8cf", "#fefefb", "#fde3de", "#f5e6dc", "#eafbfd", "#f5f2e9", "#f4ddd7", "#fef7eb", "#fef0d1", "#fedaca", "#fed9d2", "#fee2d5", "#fde9d9", "#f7f7f7", "#feede1", "#fbf9fd", "#fceee8"]}