{"Red": ["#e2b4b2", "#d29897", "#af7d82"], "Orange": [], "Yellow": [], "Yellow Green": [], "Green": [], "Blue Green": [], "Light Blue": ["#abe0e7", "#65b2b2", "#b3fbfc", "#a9d5dc", "#8ebac1", "#70a9a6", "#7fb0b1", "#5f9fa3", "#9ee8ec", "#94c7cd", "#6fc0bd", "#99d9db", "#73b1b9", "#72a5b2", "#bef4f5", "#b1e9ee", "#a3f7f5"], "Blue": ["#7da2ba", "#9dd3e8", "#7298ae", "#84abc8"], "Dark Blue": ["#656dc7", "#8c9ced", "#8287c3"], "Blue Violet": [], "Violet": [], "Violet Red": [], "Grey": ["#9c9da9", "#626978", "#c8c1c5", "#44444e", "#88879a", "#b3afb6", "#ece8e3", "#d2d2d1", "#574b53", "#7a7984", "#94959f", "#a4a6b2", "#58565f", "#b8bfcc", "#aeaaae", "#b9b4ba", "#83838d", "#706f79", "#e0dcd8", "#d4cdcd", "#c8ccd2", "#64636c", "#a7a3a8", "#b3b4bf", "#9c9aa2", "#c1bbc1", "#908f99", "#aaaeba", "#87a1a9", "#cec6c9", "#a29ea6", "#4c4a58", "#9fa2ad", "#7a7d8a", "#505868", "#898993", "#9db1c4", "#a8a5af", "#615f6c", "#9598a4", "#c1c9d6", "#b2adb1", "#696d7f", "#d6d8dd", "#a9c3cd", "#728da1", "#707582", "#938b90", "#5e5c69", "#9897a0", "#94a6bb", "#b4bbc7", "#bab1b1", "#535057", "#bfc1c7", "#8c8c96", "#c7d1e2", "#8f929e", "#bbbbb9", "#585c65", "#6b6b78", "#eecbca", "#b6b1b4", "#858894", "#4c505c", "#686770", "#a4a1ab", "#807f8a", "#e0e0e1", "#444852", "#9399aa", "#9c9ba4", "#cfcacc", "#aebdd5", "#6d7391", "#dbd2ce", "#79747c", "#b7c6dd", "#bcc4d1", "#7a7fa0", "#87868e", "#92919b", "#b0b6c2", "#b8b8b7", "#aaa6ab", "#a5919b", "#e8e3db", "#c5cad1", "#c6bfb7", "#9a979b", "#4e484c", "#505261", "#5e6574", "#e4e6ec", "#a7a9b5", "#beb8be", "#7f7c84", "#666573", "#7c8191", "#aca9b1", "#9593ac", "#5e575b", "#a09ba2", "#9d9fab", "#aeaab3", "#d7d0cf", "#93a1b2", "#9899a5", "#d2d1d5", "#cab4b6", "#ccc5c7", "#a1a3af", "#c6bfc3", "#777681", "#babcc4", "#ddd9d5", "#c2d5da", "#85818b", "#d1bfc1", "#7e90a5", "#c5c7cd", "#a09ea8", "#5e5c65", "#afa9ac", "#747a8a", "#a2a9ba", "#adb0b8", "#d2cbc9", "#ac9fac", "#aab2c3", "#686e8d", "#998d9a", "#595765", "#8a8389", "#8b8e9b", "#f1d4d1", "#b4b4b8", "#8d8991", "#a396a3", "#71717d", "#6d6d7a", "#504e56", "#adb2be", "#9c9a9e", "#c7c6c7", "#7c7c87", "#585b7d", "#9998a1", "#888191", "#7f7688", "#727895", "#414453", "#c4c3be", "#96a9af", "#a6a19f", "#a5a1a8", "#637b80", "#6e6a6e", "#aaaaaf", "#8c93a5", "#90888c", "#b8bac0", "#4a5063", "#b6afad", "#6b6973", "#50535c", "#95949e", "#b6b2b9", "#a7b6cd", "#5b5c6b", "#6d5c60", "#bfbaba", "#4b4452", "#9d9ca5", "#9696a1", "#d2d0dc", "#b8b1b5", "#a2b3c9", "#a69ba2", "#878a96", "#75999c", "#b4aeb2", "#575458", "#ecc0c1", "#b7a89f", "#a0bec9", "#4e4c52", "#c1ccdf", "#c3bdc2", "#7e8595", "#ede7df", "#cdd6e9", "#838692", "#a1a2be", "#656571", "#7d797d", "#9294a1", "#747782", "#5a6273", "#c1ebed", "#ccc4c3", "#b9cfd3", "#9aa4ab", "#d1cacb", "#82828c", "#515570", "#aaadb3", "#e3e3e4", "#969cad", "#adabaa", "#a7a4ae", "#444c5f", "#989ba8", "#b4c3d9", "#565963", "#c4abad", "#a39491", "#868691", "#d0cdd0", "#8d9ab4", "#bec7d4", "#73737f", "#887b7d", "#b6b7bc", "#98acc0", "#9690a1", "#5c5a62", "#a09da4", "#a29fa9", "#766b77", "#514d5c", "#b5dfe3", "#6f8196", "#908bab", "#6d6b75", "#a4a5a9", "#776a6d", "#6e6a7e", "#aca7ac", "#5e4c4e", "#696976", "#b6b5b4", "#b8b7be", "#b1acb0", "#61616f", "#6a717c", "#f0ece6", "#bcb7bd", "#868c9d", "#c4c4c9", "#8daeb1", "#b1b1b5", "#9da0b1", "#dad5d7", "#bebec4", "#3f4759", "#474555", "#403f4f", "#b7d6db", "#b9aab2", "#838085", "#8da4ab", "#888792", "#54515a", "#a398b4", "#757286", "#cccccf", "#625d60", "#c0beba", "#9f969f", "#968f94", "#aba7b0", "#a8a4aa", "#a1c9d3", "#dbdadb", "#8d8d97", "#5b6a79", "#cfc8c5", "#b0abaf", "#4c506c", "#7d8c9a", "#afacb4", "#514a4f", "#5e5e6d", "#666c7a", "#787c87", "#a6a9b4", "#beb8b8", "#859097", "#a1acbd", "#c9b9be", "#aea6a9", "#d9dceb", "#8e8e98", "#76878f", "#666065", "#938d99", "#9196a6", "#c9c6ca", "#baa5aa", "#b2b8c4", "#4e5466", "#6c7182", "#79768a", "#c4ced5", "#565a6b", "#817f94", "#cbc9cb", "#a9acb8", "#a1a6ac", "#908d9e", "#e9e4df", "#c9c2c1", "#cbe3e4", "#9696a0", "#61878c", "#75757f", "#9f9da6", "#9c9eaa", "#eceaec", "#f2e1df", "#555260", "#49414e", "#a69aa8", "#908e95", "#958795", "#b2b1b0", "#84848e", "#bfc2ca", "#676874", "#9b9ca8", "#b7bdc9", "#c0babf", "#9b8fae", "#f2efe9", "#52555f", "#d4d5d7", "#7e7d88", "#98949d", "#4f686d", "#ddd6d0", "#bfafb5", "#a7abb6", "#d6cac7", "#636987", "#9b98a1", "#c4c3c6", "#b1c2c8", "#524e53", "#e5dcd7", "#bbb5b7", "#847c8e", "#726f82", "#838899", "#8b8a94", "#b0adc6", "#bac2ce", "#deddde", "#74737d", "#d6cdcb", "#8f8898", "#4b4755", "#cad1d8", "#898c99", "#999eaf", "#eddad5", "#8788a7", "#d6cece", "#a2a4b0", "#a9bac6", "#91909a", "#ebdedc", "#cfc8c9", "#93929d", "#c1d0e4", "#beb7c8", "#d1cdce", "#a8a5a4", "#848397", "#b0b2bc", "#63616a", "#c6cbdb", "#4b4e58", "#dfcbca", "#44404d", "#b2acab", "#9da7ae", "#aeabba", "#747278", "#abb9d1", "#6e737e", "#81818b", "#9d97a5", "#5e5157", "#9f9999", "#b1adb5", "#8d909c", "#e1d3de", "#b5b0b7", "#8e97a9", "#615f67", "#c1c5cc", "#9e9da1", "#a5a8af", "#c3bfbd", "#8e8284", "#7a7275", "#6f6e77", "#a2a2a6", "#ad999f", "#9798a4", "#767985", "#9799a6", "#91939f", "#cfd8dd", "#8b8b95", "#f0eef2", "#a7a8ac", "#818490", "#c7c5c1", "#636871", "#5f636d", "#9e949a", "#d8d4d2", "#a19d9e", "#4e4c5a", "#bec6da", "#535463", "#717786", "#e2d7d5", "#c8c9ce", "#7f828e", "#8593a1", "#a6a3ad", "#4a4c5e", "#3b4153", "#66656e", "#8ca6b4", "#a29fa2", "#b5afb4", "#777e8d", "#7e9da5", "#bcbbc0", "#bdcce3", "#626074", "#7d7a8f", "#8595ab", "#5b585f", "#b4bace", "#939198", "#c6bfbf", "#8f97a0", "#8c8a9d", "#bcb6b4", "#a2acb2", "#bbbfc8", "#b5b7c0", "#9fa5b6", "#a7a8c4", "#9a9297", "#54484b", "#aba3a7", "#9b9aa3", "#66575b", "#cac3c6", "#d8d0ca", "#d3cbcc", "#c4becd", "#a3a0a6", "#435d62", "#8182a2", "#cdced3", "#585e6f", "#8d858e", "#8e8b94", "#e7e6e7", "#a7a1b6", "#3f444d", "#7a7082", "#9a9ab7", "#454252", "#7b7a86", "#5f6681", "#5d616a", "#72717b", "#8c8494", "#9b8d92", "#b3a6ae", "#bbafbf", "#aaa6b0", "#c5b5b0", "#8a8fa0", "#aeaeb3", "#dcc2bf", "#85a1b0", "#9496a1", "#b9c0d4", "#7d7f8b", "#c3b4ba", "#b3b5bc", "#b4a7b7", "#96969f", "#887f85", "#575563", "#929ba4", "#484d56", "#6f7088", "#6d636f", "#54777a", "#777d99", "#c2bfc4", "#9a9caa", "#a6aebf", "#514957", "#9a969f", "#696d77", "#9e9ca6", "#474a54", "#364d54", "#b9b3b6", "#ada9ad", "#9abac2", "#a8a0a4", "#b1b2b9", "#cbc0bd", "#707e86", "#565056", "#636370", "#bbb5bb", "#625765", "#696c87", "#b0aeae", "#8a8890", "#5a5a68", "#9994a4", "#96959f", "#969fa7", "#8f9dae", "#969499", "#6b9095", "#a6afb6", "#98a4b5", "#b0ccd1", "#6a798c", "#767684", "#bfbfbf", "#a0a2ae", "#978788", "#acb0bc", "#8d92a1", "#47485a", "#9d909f", "#b7b9c4", "#aeb5ca", "#4a4950", "#627083", "#827c89", "#817677", "#95919b", "#74748d", "#9a9ba7", "#726e73", "#9496a3", "#d8c7d4", "#bac9e0", "#afb4c0", "#837b81", "#a3999d", "#999aa6", "#787882", "#e1dad2", "#58545c", "#9697a2", "#b7b3ba", "#545975", "#93a5ac", "#5d617c", "#e4dfdb", "#e8dde5", "#5a5e68", "#7c7782", "#474551", "#c8c4d1", "#54545c", "#9ba9ba", "#beada8", "#85858f", "#9998a2", "#a2a6b1", "#524344", "#68677a", "#aba8a7", "#555767", "#c1c7d2", "#c2bbbc", "#53505e", "#4e5159", "#696569", "#545861", "#9ea1ac", "#a3a0aa", "#9f9bac", "#7ea7aa", "#9e9ba4", "#d8dee2", "#b6b3b0", "#d3c5c5", "#cccad6", "#d0baba", "#6e6f7c", "#716468", "#e4d2d0", "#a5a2ac", "#9190a3", "#a4a8b3", "#4f505f", "#b29fa6"], "Black": ["#2e2c3d", "#373b4c", "#110f1f", "#1a182a", "#353344", "#43393b", "#403d45", "#473e48", "#3d3e4b", "#35303e", "#2b2939", "#3d3a43", "#222133", "#474244", "#131327", "#362a32", "#312f41", "#3c3538", "#49474c", "#37373d", "#353945", "#414048", "#393647", "#2c222a", "#3d3949", "#4b4547", "#2e353f", "#393441", "#262537", "#464449", "#3b3a3f", "#3f3d40", "#3a3d47", "#1f1d2f", "#2e2f31", "#463e40", "#403b4c", "#343337"], "White": ["#faeff3", "#fefefe", "#f9e8e5", "#fae4de", "#f3f3f7", "#f7ecea", "#f4e9e4", "#f7f6fa", "#faf6f2", "#f6e4e3", "#fbeeed", "#f5f1ec", "#f4ded9", "#fdfdfd", "#d8f9fa", "#e9ecf3", "#e0e2f3", "#fbfafb"]}